pyvlx/__init__.py
pyvlx/config.py
pyvlx/connection.py
pyvlx/const.py
pyvlx/dataobjects.py
pyvlx/discovery.py
pyvlx/exception.py
pyvlx/heartbeat.py
pyvlx/klf200gateway.py
pyvlx/lightening_device.py
pyvlx/log.py
pyvlx/node.py
pyvlx/node_helper.py
pyvlx/node_updater.py
pyvlx/nodes.py
pyvlx/on_off_switch.py
pyvlx/opening_device.py
pyvlx/parameter.py
pyvlx/py.typed
pyvlx/pyvlx.py
pyvlx/scene.py
pyvlx/scenes.py
pyvlx/slip.py
pyvlx/string_helper.py
pyvlx/api/__init__.py
pyvlx/api/activate_scene.py
pyvlx/api/api_event.py
pyvlx/api/command_send.py
pyvlx/api/factory_default.py
pyvlx/api/frame_creation.py
pyvlx/api/get_all_nodes_information.py
pyvlx/api/get_limitation.py
pyvlx/api/get_local_time.py
pyvlx/api/get_network_setup.py
pyvlx/api/get_node_information.py
pyvlx/api/get_protocol_version.py
pyvlx/api/get_scene_list.py
pyvlx/api/get_state.py
pyvlx/api/get_version.py
pyvlx/api/house_status_monitor.py
pyvlx/api/leave_learn_state.py
pyvlx/api/password_enter.py
pyvlx/api/reboot.py
pyvlx/api/session_id.py
pyvlx/api/set_node_name.py
pyvlx/api/set_utc.py
pyvlx/api/status_request.py
pyvlx/api/frames/__init__.py
pyvlx/api/frames/alias_array.py
pyvlx/api/frames/frame.py
pyvlx/api/frames/frame_activate_scene.py
pyvlx/api/frames/frame_activation_log_updated.py
pyvlx/api/frames/frame_command_send.py
pyvlx/api/frames/frame_discover_nodes.py
pyvlx/api/frames/frame_error_notification.py
pyvlx/api/frames/frame_facory_default.py
pyvlx/api/frames/frame_get_all_nodes_information.py
pyvlx/api/frames/frame_get_limitation.py
pyvlx/api/frames/frame_get_local_time.py
pyvlx/api/frames/frame_get_network_setup.py
pyvlx/api/frames/frame_get_node_information.py
pyvlx/api/frames/frame_get_protocol_version.py
pyvlx/api/frames/frame_get_scene_list.py
pyvlx/api/frames/frame_get_state.py
pyvlx/api/frames/frame_get_version.py
pyvlx/api/frames/frame_helper.py
pyvlx/api/frames/frame_house_status_monitor_disable_cfm.py
pyvlx/api/frames/frame_house_status_monitor_disable_req.py
pyvlx-0.2.28.dist-info/licenses/LICENSE
pyvlx-0.2.28.dist-info/METADATA
pyvlx-0.2.28.dist-info/WHEEL
pyvlx-0.2.28.dist-info/top_level.txt
pyvlx-0.2.28.dist-info/RECORD
