Metadata-Version: 2.4
Name: pyvlx
Version: 0.2.28
Summary: PyVLX is a wrapper for the Velux KLF 200 API. PyVLX enables you to run scenes and or open and close velux windows.
Home-page: https://github.com/Julius2342/pyvlx
Download-URL: https://github.com/Julius2342/pyvlx/archive/0.2.28.zip
Author: Julius Mittenzwei
Author-email: julius@mittenzwei.com
License: LGPL
Keywords: velux KLF 200 home automation
Classifier: Development Status :: 3 - Alpha
Classifier: Intended Audience :: End Users/Desktop
Classifier: Intended Audience :: Developers
Classifier: Topic :: System :: Hardware :: Hardware Drivers
Classifier: License :: OSI Approved :: GNU Lesser General Public License v3 (LGPLv3)
Classifier: Programming Language :: Python :: 3.11
Classifier: Programming Language :: Python :: 3.12
Classifier: Programming Language :: Python :: 3.13
Classifier: Programming Language :: Python :: 3.14
Requires-Python: >=3.11
License-File: LICENSE
Requires-Dist: PyYAML
Requires-Dist: zeroconf
Dynamic: author
Dynamic: author-email
Dynamic: classifier
Dynamic: description
Dynamic: description-content-type
Dynamic: download-url
Dynamic: home-page
Dynamic: keywords
Dynamic: license
Dynamic: license-file
Dynamic: requires-dist
Dynamic: requires-python
Dynamic: summary
